{
  "$schema": "https://developer.microsoft.com/json-schemas/fabric/item/report/definition/visualContainer/1.5.0/schema.json",
  "name": "de4394200ad8b05b3077",
  "position": {
    "x": 10.561056105610561,
    "y": 0,
    "z": 0,
    "height": 71.815181518151817,
    "width": 678.72387238723866,
    "tabOrder": 0
  },
  "visual": {
    "visualType": "slicer",
    "query": {
      "queryState": {
        "Values": {
          "projections": [
            {
              "field": {
                "Column": {
                  "Expression": {
                    "SourceRef": {
                      "Entity": "dim_calendar"
                    }
                  },
                  "Property": "date"
                }
              },
              "queryRef": "dim_calendar.date",
              "nativeQueryRef": "date",
              "active": true
            }
          ]
        }
      },
      "sortDefinition": {
        "sort": [
          {
            "field": {
              "Column": {
                "Expression": {
                  "SourceRef": {
                    "Entity": "dim_calendar"
                  }
                },
                "Property": "date"
              }
            },
            "direction": "Ascending"
          }
        ],
        "isDefaultSort": true
      }
    },
    "objects": {
      "data": [
        {
          "properties": {
            "startDate": {
              "expr": {
                "Literal": {
                  "Value": "datetime'2023-12-08T00:00:00'"
                }
              }
            },
            "endDate": {
              "expr": {
                "Literal": {
                  "Value": "datetime'2025-01-06T00:00:00'"
                }
              }
            },
            "mode": {
              "expr": {
                "Literal": {
                  "Value": "'Between'"
                }
              }
            }
          }
        }
      ],
      "header": [
        {
          "properties": {
            "show": {
              "expr": {
                "Literal": {
                  "Value": "false"
                }
              }
            }
          }
        }
      ],
      "general": [
        {
          "properties": {
            "responsive": {
              "expr": {
                "Literal": {
                  "Value": "false"
                }
              }
            },
            "filter": {
              "filter": {
                "Version": 2,
                "From": [
                  {
                    "Name": "d",
                    "Entity": "dim_calendar",
                    "Type": 0
                  }
                ],
                "Where": [
                  {
                    "Condition": {
                      "And": {
                        "Left": {
                          "Comparison": {
                            "ComparisonKind": 2,
                            "Left": {
                              "Column": {
                                "Expression": {
                                  "SourceRef": {
                                    "Source": "d"
                                  }
                                },
                                "Property": "date"
                              }
                            },
                            "Right": {
                              "Literal": {
                                "Value": "datetime'2023-12-08T00:00:00'"
                              }
                            }
                          }
                        },
                        "Right": {
                          "Comparison": {
                            "ComparisonKind": 3,
                            "Left": {
                              "Column": {
                                "Expression": {
                                  "SourceRef": {
                                    "Source": "d"
                                  }
                                },
                                "Property": "date"
                              }
                            },
                            "Right": {
                              "Literal": {
                                "Value": "datetime'2025-01-07T00:00:00'"
                              }
                            }
                          }
                        }
                      }
                    }
                  }
                ]
              }
            }
          }
        }
      ],
      "dateRange": [
        {
          "properties": {
            "includeToday": {
              "expr": {
                "Literal": {
                  "Value": "true"
                }
              }
            }
          }
        }
      ]
    },
    "visualContainerObjects": {
      "general": [
        {
          "properties": {
            "keepLayerOrder": {
              "expr": {
                "Literal": {
                  "Value": "true"
                }
              }
            }
          }
        }
      ],
      "title": [
        {
          "properties": {
            "show": {
              "expr": {
                "Literal": {
                  "Value": "false"
                }
              }
            }
          }
        }
      ]
    },
    "drillFilterOtherVisuals": true
  }
}