{
  "$schema": "https://developer.microsoft.com/json-schemas/fabric/item/report/definition/visualContainer/1.5.0/schema.json",
  "name": "00fd8d5211c45a3da3d0",
  "position": {
    "x": 9.6292315959161741,
    "y": 526.16872649113384,
    "z": 3000,
    "height": 180.20419129500269,
    "width": 1262.11714132187,
    "tabOrder": 1000
  },
  "visual": {
    "visualType": "columnChart",
    "query": {
      "queryState": {
        "Category": {
          "projections": [
            {
              "field": {
                "Column": {
                  "Expression": {
                    "SourceRef": {
                      "Entity": "dim_calendar"
                    }
                  },
                  "Property": "date"
                }
              },
              "queryRef": "dim_calendar.date",
              "nativeQueryRef": "Date",
              "active": true,
              "displayName": "Date",
              "format": "M/d"
            }
          ]
        },
        "Series": {
          "projections": [
            {
              "field": {
                "Column": {
                  "Expression": {
                    "SourceRef": {
                      "Entity": "dim_score_buckets"
                    }
                  },
                  "Property": "score_bucket"
                }
              },
              "queryRef": "select_score_buckets.score_bucket",
              "nativeQueryRef": "Score",
              "displayName": "Score"
            }
          ]
        },
        "Tooltips": {
          "projections": [
            {
              "field": {
                "Measure": {
                  "Expression": {
                    "SourceRef": {
                      "Entity": "Measure Table"
                    }
                  },
                  "Property": "Session Adjustment Most Recent"
                }
              },
              "queryRef": "Measure Table.Session Adjustment Most Recent",
              "nativeQueryRef": "Session Adjustment Most Recent"
            }
          ]
        },
        "Y": {
          "projections": [
            {
              "field": {
                "Measure": {
                  "Expression": {
                    "SourceRef": {
                      "Entity": "Measure Table"
                    }
                  },
                  "Property": "Shot Percentage"
                }
              },
              "queryRef": "Measure Table.Shot Percentage",
              "nativeQueryRef": "Shot Percentage"
            }
          ]
        }
      },
      "sortDefinition": {
        "sort": [
          {
            "field": {
              "Column": {
                "Expression": {
                  "SourceRef": {
                    "Entity": "dim_score_buckets"
                  }
                },
                "Property": "score_bucket"
              }
            },
            "direction": "Ascending"
          }
        ]
      }
    },
    "objects": {
      "categoryAxis": [
        {
          "properties": {
            "axisType": {
              "expr": {
                "Literal": {
                  "Value": "'Categorical'"
                }
              }
            },
            "show": {
              "expr": {
                "Literal": {
                  "Value": "true"
                }
              }
            },
            "showAxisTitle": {
              "expr": {
                "Literal": {
                  "Value": "false"
                }
              }
            },
            "innerPadding": {
              "expr": {
                "Literal": {
                  "Value": "15L"
                }
              }
            },
            "concatenateLabels": {
              "expr": {
                "Literal": {
                  "Value": "false"
                }
              }
            },
            "maxMarginFactor": {
              "expr": {
                "Literal": {
                  "Value": "15L"
                }
              }
            }
          }
        }
      ],
      "ribbonBands": [
        {
          "properties": {
            "show": {
              "expr": {
                "Literal": {
                  "Value": "false"
                }
              }
            },
            "fillTransparency": {
              "expr": {
                "Literal": {
                  "Value": "0D"
                }
              }
            },
            "borderShow": {
              "expr": {
                "Literal": {
                  "Value": "false"
                }
              }
            },
            "fillMatchColor": {
              "expr": {
                "Literal": {
                  "Value": "true"
                }
              }
            }
          }
        }
      ],
      "dataPoint": [
        {
          "properties": {
            "fill": {
              "solid": {
                "color": {
                  "expr": {
                    "ThemeDataColor": {
                      "ColorId": 2,
                      "Percent": 0
                    }
                  }
                }
              }
            }
          },
          "selector": {
            "data": [
              {
                "scopeId": {
                  "Comparison": {
                    "ComparisonKind": 0,
                    "Left": {
                      "Column": {
                        "Expression": {
                          "SourceRef": {
                            "Entity": "fact_shot_score"
                          }
                        },
                        "Property": "score"
                      }
                    },
                    "Right": {
                      "Literal": {
                        "Value": "10L"
                      }
                    }
                  }
                }
              }
            ]
          }
        },
        {
          "properties": {
            "fill": {
              "solid": {
                "color": {
                  "expr": {
                    "ThemeDataColor": {
                      "ColorId": 2,
                      "Percent": 0.6
                    }
                  }
                }
              }
            }
          },
          "selector": {
            "data": [
              {
                "scopeId": {
                  "Comparison": {
                    "ComparisonKind": 0,
                    "Left": {
                      "Column": {
                        "Expression": {
                          "SourceRef": {
                            "Entity": "fact_shot_score"
                          }
                        },
                        "Property": "score"
                      }
                    },
                    "Right": {
                      "Literal": {
                        "Value": "9L"
                      }
                    }
                  }
                }
              }
            ]
          }
        },
        {
          "properties": {
            "fill": {
              "solid": {
                "color": {
                  "expr": {
                    "ThemeDataColor": {
                      "ColorId": 3,
                      "Percent": 0
                    }
                  }
                }
              }
            }
          },
          "selector": {
            "data": [
              {
                "scopeId": {
                  "Comparison": {
                    "ComparisonKind": 0,
                    "Left": {
                      "Column": {
                        "Expression": {
                          "SourceRef": {
                            "Entity": "fact_shot_score"
                          }
                        },
                        "Property": "score"
                      }
                    },
                    "Right": {
                      "Literal": {
                        "Value": "8L"
                      }
                    }
                  }
                }
              }
            ]
          }
        },
        {
          "properties": {
            "fill": {
              "solid": {
                "color": {
                  "expr": {
                    "ThemeDataColor": {
                      "ColorId": 3,
                      "Percent": 0.4
                    }
                  }
                }
              }
            }
          },
          "selector": {
            "data": [
              {
                "scopeId": {
                  "Comparison": {
                    "ComparisonKind": 0,
                    "Left": {
                      "Column": {
                        "Expression": {
                          "SourceRef": {
                            "Entity": "fact_shot_score"
                          }
                        },
                        "Property": "score"
                      }
                    },
                    "Right": {
                      "Literal": {
                        "Value": "7L"
                      }
                    }
                  }
                }
              }
            ]
          }
        },
        {
          "properties": {
            "fill": {
              "solid": {
                "color": {
                  "expr": {
                    "ThemeDataColor": {
                      "ColorId": 4,
                      "Percent": 0
                    }
                  }
                }
              }
            }
          },
          "selector": {
            "data": [
              {
                "scopeId": {
                  "Comparison": {
                    "ComparisonKind": 0,
                    "Left": {
                      "Column": {
                        "Expression": {
                          "SourceRef": {
                            "Entity": "fact_shot_score"
                          }
                        },
                        "Property": "score"
                      }
                    },
                    "Right": {
                      "Literal": {
                        "Value": "6L"
                      }
                    }
                  }
                }
              }
            ]
          }
        },
        {
          "properties": {
            "fill": {
              "solid": {
                "color": {
                  "expr": {
                    "ThemeDataColor": {
                      "ColorId": 4,
                      "Percent": 0.4
                    }
                  }
                }
              }
            }
          },
          "selector": {
            "data": [
              {
                "scopeId": {
                  "Comparison": {
                    "ComparisonKind": 0,
                    "Left": {
                      "Column": {
                        "Expression": {
                          "SourceRef": {
                            "Entity": "fact_shot_score"
                          }
                        },
                        "Property": "score"
                      }
                    },
                    "Right": {
                      "Literal": {
                        "Value": "5L"
                      }
                    }
                  }
                }
              }
            ]
          }
        },
        {
          "properties": {
            "fill": {
              "solid": {
                "color": {
                  "expr": {
                    "ThemeDataColor": {
                      "ColorId": 5,
                      "Percent": 0
                    }
                  }
                }
              }
            }
          },
          "selector": {
            "data": [
              {
                "scopeId": {
                  "Comparison": {
                    "ComparisonKind": 0,
                    "Left": {
                      "Column": {
                        "Expression": {
                          "SourceRef": {
                            "Entity": "fact_shot_score"
                          }
                        },
                        "Property": "score"
                      }
                    },
                    "Right": {
                      "Literal": {
                        "Value": "4L"
                      }
                    }
                  }
                }
              }
            ]
          }
        },
        {
          "properties": {
            "fill": {
              "solid": {
                "color": {
                  "expr": {
                    "ThemeDataColor": {
                      "ColorId": 5,
                      "Percent": 0.4
                    }
                  }
                }
              }
            }
          },
          "selector": {
            "data": [
              {
                "scopeId": {
                  "Comparison": {
                    "ComparisonKind": 0,
                    "Left": {
                      "Column": {
                        "Expression": {
                          "SourceRef": {
                            "Entity": "fact_shot_score"
                          }
                        },
                        "Property": "score"
                      }
                    },
                    "Right": {
                      "Literal": {
                        "Value": "3L"
                      }
                    }
                  }
                }
              }
            ]
          }
        },
        {
          "properties": {
            "fill": {
              "solid": {
                "color": {
                  "expr": {
                    "ThemeDataColor": {
                      "ColorId": 2,
                      "Percent": 0
                    }
                  }
                }
              }
            }
          },
          "selector": {
            "data": [
              {
                "scopeId": {
                  "Comparison": {
                    "ComparisonKind": 0,
                    "Left": {
                      "Column": {
                        "Expression": {
                          "SourceRef": {
                            "Entity": "dim_score_buckets"
                          }
                        },
                        "Property": "score_bucket"
                      }
                    },
                    "Right": {
                      "Literal": {
                        "Value": "'10'"
                      }
                    }
                  }
                }
              }
            ]
          }
        },
        {
          "properties": {
            "fill": {
              "solid": {
                "color": {
                  "expr": {
                    "ThemeDataColor": {
                      "ColorId": 2,
                      "Percent": 0.4
                    }
                  }
                }
              }
            }
          },
          "selector": {
            "data": [
              {
                "scopeId": {
                  "Comparison": {
                    "ComparisonKind": 0,
                    "Left": {
                      "Column": {
                        "Expression": {
                          "SourceRef": {
                            "Entity": "dim_score_buckets"
                          }
                        },
                        "Property": "score_bucket"
                      }
                    },
                    "Right": {
                      "Literal": {
                        "Value": "'9'"
                      }
                    }
                  }
                }
              }
            ]
          }
        },
        {
          "properties": {
            "fill": {
              "solid": {
                "color": {
                  "expr": {
                    "ThemeDataColor": {
                      "ColorId": 3,
                      "Percent": 0
                    }
                  }
                }
              }
            }
          },
          "selector": {
            "data": [
              {
                "scopeId": {
                  "Comparison": {
                    "ComparisonKind": 0,
                    "Left": {
                      "Column": {
                        "Expression": {
                          "SourceRef": {
                            "Entity": "dim_score_buckets"
                          }
                        },
                        "Property": "score_bucket"
                      }
                    },
                    "Right": {
                      "Literal": {
                        "Value": "'8'"
                      }
                    }
                  }
                }
              }
            ]
          }
        },
        {
          "properties": {
            "fill": {
              "solid": {
                "color": {
                  "expr": {
                    "ThemeDataColor": {
                      "ColorId": 3,
                      "Percent": 0.4
                    }
                  }
                }
              }
            }
          },
          "selector": {
            "data": [
              {
                "scopeId": {
                  "Comparison": {
                    "ComparisonKind": 0,
                    "Left": {
                      "Column": {
                        "Expression": {
                          "SourceRef": {
                            "Entity": "dim_score_buckets"
                          }
                        },
                        "Property": "score_bucket"
                      }
                    },
                    "Right": {
                      "Literal": {
                        "Value": "'7'"
                      }
                    }
                  }
                }
              }
            ]
          }
        },
        {
          "properties": {
            "fill": {
              "solid": {
                "color": {
                  "expr": {
                    "ThemeDataColor": {
                      "ColorId": 4,
                      "Percent": 0
                    }
                  }
                }
              }
            }
          },
          "selector": {
            "data": [
              {
                "scopeId": {
                  "Comparison": {
                    "ComparisonKind": 0,
                    "Left": {
                      "Column": {
                        "Expression": {
                          "SourceRef": {
                            "Entity": "dim_score_buckets"
                          }
                        },
                        "Property": "score_bucket"
                      }
                    },
                    "Right": {
                      "Literal": {
                        "Value": "'6'"
                      }
                    }
                  }
                }
              }
            ]
          }
        },
        {
          "properties": {
            "fill": {
              "solid": {
                "color": {
                  "expr": {
                    "ThemeDataColor": {
                      "ColorId": 4,
                      "Percent": 0.4
                    }
                  }
                }
              }
            }
          },
          "selector": {
            "data": [
              {
                "scopeId": {
                  "Comparison": {
                    "ComparisonKind": 0,
                    "Left": {
                      "Column": {
                        "Expression": {
                          "SourceRef": {
                            "Entity": "dim_score_buckets"
                          }
                        },
                        "Property": "score_bucket"
                      }
                    },
                    "Right": {
                      "Literal": {
                        "Value": "'5'"
                      }
                    }
                  }
                }
              }
            ]
          }
        },
        {
          "properties": {
            "fill": {
              "solid": {
                "color": {
                  "expr": {
                    "ThemeDataColor": {
                      "ColorId": 5,
                      "Percent": 0.2
                    }
                  }
                }
              }
            }
          },
          "selector": {
            "data": [
              {
                "scopeId": {
                  "Comparison": {
                    "ComparisonKind": 0,
                    "Left": {
                      "Column": {
                        "Expression": {
                          "SourceRef": {
                            "Entity": "dim_score_buckets"
                          }
                        },
                        "Property": "score_bucket"
                      }
                    },
                    "Right": {
                      "Literal": {
                        "Value": "'< 5'"
                      }
                    }
                  }
                }
              }
            ]
          }
        },
        {
          "properties": {
            "borderShow": {
              "expr": {
                "Literal": {
                  "Value": "false"
                }
              }
            },
            "borderOutlineOnly": {
              "expr": {
                "Literal": {
                  "Value": "true"
                }
              }
            },
            "borderColorMatchFill": {
              "expr": {
                "Literal": {
                  "Value": "false"
                }
              }
            }
          }
        }
      ],
      "valueAxis": [
        {
          "properties": {
            "showAxisTitle": {
              "expr": {
                "Literal": {
                  "Value": "false"
                }
              }
            },
            "show": {
              "expr": {
                "Literal": {
                  "Value": "true"
                }
              }
            },
            "invertAxis": {
              "expr": {
                "Literal": {
                  "Value": "false"
                }
              }
            },
            "end": {
              "expr": {
                "Literal": {
                  "Value": "1D"
                }
              }
            },
            "start": {
              "expr": {
                "Literal": {
                  "Value": "0D"
                }
              }
            }
          }
        }
      ],
      "legend": [
        {
          "properties": {
            "showTitle": {
              "expr": {
                "Literal": {
                  "Value": "false"
                }
              }
            },
            "position": {
              "expr": {
                "Literal": {
                  "Value": "'TopRight'"
                }
              }
            },
            "fontSize": {
              "expr": {
                "Literal": {
                  "Value": "8D"
                }
              }
            },
            "showGradientLegend": {
              "expr": {
                "Literal": {
                  "Value": "true"
                }
              }
            },
            "show": {
              "expr": {
                "Literal": {
                  "Value": "true"
                }
              }
            }
          }
        }
      ],
      "layout": [
        {
          "properties": {
            "ribbonGapSize": {
              "expr": {
                "Literal": {
                  "Value": "0D"
                }
              }
            },
            "stackedGapExplodes": {
              "expr": {
                "Literal": {
                  "Value": "false"
                }
              }
            },
            "stackedGapSize": {
              "expr": {
                "Literal": {
                  "Value": "0D"
                }
              }
            }
          }
        }
      ],
      "general": [
        {
          "properties": {
            "responsive": {
              "expr": {
                "Literal": {
                  "Value": "false"
                }
              }
            }
          }
        }
      ],
      "labels": [
        {
          "properties": {
            "show": {
              "expr": {
                "Literal": {
                  "Value": "false"
                }
              }
            },
            "labelOrientation": {
              "expr": {
                "Literal": {
                  "Value": "0D"
                }
              }
            }
          }
        }
      ]
    },
    "visualContainerObjects": {
      "visualHeader": [
        {
          "properties": {
            "show": {
              "expr": {
                "Literal": {
                  "Value": "false"
                }
              }
            }
          }
        }
      ],
      "general": [
        {
          "properties": {
            "keepLayerOrder": {
              "expr": {
                "Literal": {
                  "Value": "true"
                }
              }
            }
          }
        }
      ],
      "title": [
        {
          "properties": {
            "show": {
              "expr": {
                "Literal": {
                  "Value": "false"
                }
              }
            }
          }
        }
      ],
      "spacing": [
        {
          "properties": {
            "customizeSpacing": {
              "expr": {
                "Literal": {
                  "Value": "false"
                }
              }
            },
            "spaceBelowTitle": {
              "expr": {
                "Literal": {
                  "Value": "0D"
                }
              }
            }
          }
        }
      ]
    },
    "drillFilterOtherVisuals": true
  }
}